README.md
setup.py
airbridge/__init__.py
airbridge.egg-info/PKG-INFO
airbridge.egg-info/SOURCES.txt
airbridge.egg-info/dependency_links.txt
airbridge.egg-info/not-zip-safe
airbridge.egg-info/requires.txt
airbridge.egg-info/top_level.txt
airbridge/models/__init__.py
airbridge/models/app_resource.py
airbridge/models/simplelink.py
airbridge/testing/__init__.py
airbridge/testing/config.py
airbridge/testing/sample.py
airbridge/utils/__init__.py
airbridge/utils/events.py
airbridge/utils/exceptions.py
airbridge/utils/tools.py
airbridge/utils/user_agents.py
airbridge/worker/__init__.py
airbridge/worker/kafka_worker.py