Metadata-Version: 1.0
Name: airbridge
Version: 0.2.1
Summary: airbridge utilities
Home-page: http://github.com/HunjaeJung/airbridge
Author: hunjae
Author-email: hunjae@ab180.co
License: MIT
Platform: UNKNOWN
